catkin_lint/__init__.py
catkin_lint/__main__.py
catkin_lint/_version.py
catkin_lint/cmake.py
catkin_lint/diagnostics.py
catkin_lint/environment.py
catkin_lint/linter.py
catkin_lint/looseversion.py
catkin_lint/main.py
catkin_lint/output.py
catkin_lint/ros.py
catkin_lint/util.py
catkin_lint/checks/__init__.py
catkin_lint/checks/build.py
catkin_lint/checks/cuda.py
catkin_lint/checks/manifest.py
catkin_lint/checks/misc.py
catkin_lint/checks/python.py
catkin_lint-1.6.25.data/data/share/bash-completion/completions/catkin_lint
catkin_lint-1.6.25.data/data/share/fish/vendor_completions.d/catkin_lint.fish
catkin_lint-1.6.25.data/scripts/catkin_lint
catkin_lint-1.6.25.dist-info/LICENSE
catkin_lint-1.6.25.dist-info/METADATA
catkin_lint-1.6.25.dist-info/WHEEL
catkin_lint-1.6.25.dist-info/entry_points.txt
catkin_lint-1.6.25.dist-info/top_level.txt
catkin_lint-1.6.25.dist-info/RECORD
