Metadata-Version: 2.1
Name: catkin_lint
Version: 1.6.25
Summary: Check catkin packages for common errors
Home-page: https://github.com/fkie/catkin_lint
Author: Timo Röhling
Author-email: timo.roehling@fkie.fraunhofer.de
License: BSD
Keywords: catkin,ROS
Classifier: Development Status :: 5 - Production/Stable
Classifier: Intended Audience :: Developers
Classifier: License :: OSI Approved :: BSD License
Classifier: Topic :: Software Development :: Quality Assurance
Classifier: Environment :: Console
Classifier: Operating System :: OS Independent
Classifier: Programming Language :: Python
Classifier: Programming Language :: Python :: 3
License-File: LICENSE
Requires-Dist: catkin-pkg
Requires-Dist: lxml
Requires-Dist: configparser<5; python_version < "3"
Provides-Extra: ros
Requires-Dist: rosdep; extra == "ros"
Requires-Dist: rosdistro; extra == "ros"
